[
  {
    "maskFrame" : null,
    "id" : "CD7C7C7A-40BD-4449-884D-CE043DD9C73B",
    "visible" : true,
    "children" : [
      {
        "maskFrame" : {
          "y" : 67,
          "x" : 0,
          "width" : 900,
          "height" : 1853
        },
        "id" : "BD451A6E-CC1D-4103-8C28-8A5D77EF8CC8",
        "visible" : true,
        "children" : [

        ],
        "image" : {
          "path" : "images\/Layer-drawer-BD451A6E-CC1D-4103-8C28-8A5D77EF8CC8.png",
          "frame" : {
            "y" : 67,
            "x" : 0,
            "width" : 900,
            "height" : 1853
          }
        },
        "imageType" : "png",
        "layerFrame" : {
          "y" : 67,
          "x" : 0,
          "width" : 900,
          "height" : 1853
        },
        "name" : "drawer"
      },
      {
        "maskFrame" : null,
        "id" : "C17100EF-42F5-4552-AB54-2D3BD0FF7557",
        "visible" : true,
        "children" : [
          {
            "maskFrame" : null,
            "id" : "3A502647-1C84-4C5B-ADA5-B2E0BA72EBDA",
            "visible" : true,
            "children" : [
              {
                "maskFrame" : null,
                "id" : "72DAD55F-49E4-42E1-9F19-0948BFDE3D53",
                "visible" : true,
                "children" : [

                ],
                "image" : {
                  "path" : "images\/Layer-wifi-72DAD55F-49E4-42E1-9F19-0948BFDE3D53.png",
                  "frame" : {
                    "y" : 17,
                    "x" : 753,
                    "width" : 42,
                    "height" : 34
                  }
                },
                "imageType" : "png",
                "layerFrame" : {
                  "y" : 17,
                  "x" : 753,
                  "width" : 42,
                  "height" : 34
                },
                "name" : "wifi"
              },
              {
                "maskFrame" : null,
                "id" : "0A9DB09D-B5E8-49AC-B386-DD589892D832",
                "visible" : true,
                "children" : [

                ],
                "image" : {
                  "path" : "images\/Layer-Signal_-0A9DB09D-B5E8-49AC-B386-DD589892D832.png",
                  "frame" : {
                    "y" : 17,
                    "x" : 828,
                    "width" : 36,
                    "height" : 34
                  }
                },
                "imageType" : "png",
                "layerFrame" : {
                  "y" : 17,
                  "x" : 828,
                  "width" : 36,
                  "height" : 34
                },
                "name" : "Signal_"
              },
              {
                "maskFrame" : null,
                "id" : "901C847F-0089-428E-97AE-BADA328BE067",
                "visible" : true,
                "children" : [

                ],
                "image" : {
                  "path" : "images\/Layer-Battery-901C847F-0089-428E-97AE-BADA328BE067.png",
                  "frame" : {
                    "y" : 14,
                    "x" : 904,
                    "width" : 26,
                    "height" : 39
                  }
                },
                "imageType" : "png",
                "layerFrame" : {
                  "y" : 14,
                  "x" : 904,
                  "width" : 26,
                  "height" : 39
                },
                "name" : "Battery"
              }
            ],
            "image" : {
              "path" : "images\/Layer-statusBar-3A502647-1C84-4C5B-ADA5-B2E0BA72EBDA.png",
              "frame" : {
                "y" : 0,
                "x" : 0,
                "width" : 1080,
                "height" : 69
              }
            },
            "imageType" : "png",
            "layerFrame" : {
              "y" : 0,
              "x" : 0,
              "width" : 1080,
              "height" : 69
            },
            "name" : "statusBar"
          }
        ],
        "image" : {
          "path" : "images\/Layer-header-C17100EF-42F5-4552-AB54-2D3BD0FF7557.png",
          "frame" : {
            "y" : -19,
            "x" : -20,
            "width" : 1120,
            "height" : 284
          }
        },
        "imageType" : "png",
        "layerFrame" : {
          "y" : -19,
          "x" : -20,
          "width" : 1120,
          "height" : 284
        },
        "name" : "header"
      },
      {
        "maskFrame" : {
          "y" : 1920,
          "x" : 0,
          "width" : 1080,
          "height" : 1675
        },
        "id" : "29B41A15-BCF6-497C-A793-E45BF7C670E9",
        "visible" : true,
        "children" : [
          {
            "maskFrame" : null,
            "id" : "F610515A-A978-4290-ABFC-60A7387063B7",
            "visible" : true,
            "children" : [

            ],
            "image" : {
              "path" : "images\/Layer-item5-F610515A-A978-4290-ABFC-60A7387063B7.png",
              "frame" : {
                "y" : 3260,
                "x" : 0,
                "width" : 1080,
                "height" : 335
              }
            },
            "imageType" : "png",
            "layerFrame" : {
              "y" : 3260,
              "x" : 0,
              "width" : 1080,
              "height" : 335
            },
            "name" : "item5"
          },
          {
            "maskFrame" : null,
            "id" : "55E6FE49-F75F-4E21-B726-7B0E9EFF152F",
            "visible" : true,
            "children" : [

            ],
            "image" : {
              "path" : "images\/Layer-item4-55E6FE49-F75F-4E21-B726-7B0E9EFF152F.png",
              "frame" : {
                "y" : 2925,
                "x" : 0,
                "width" : 1080,
                "height" : 335
              }
            },
            "imageType" : "png",
            "layerFrame" : {
              "y" : 2925,
              "x" : 0,
              "width" : 1080,
              "height" : 335
            },
            "name" : "item4"
          },
          {
            "maskFrame" : null,
            "id" : "3C87620C-D6F1-4E50-9F43-AC66EB9F81D2",
            "visible" : true,
            "children" : [

            ],
            "image" : {
              "path" : "images\/Layer-item3-3C87620C-D6F1-4E50-9F43-AC66EB9F81D2.png",
              "frame" : {
                "y" : 2590,
                "x" : 0,
                "width" : 1080,
                "height" : 335
              }
            },
            "imageType" : "png",
            "layerFrame" : {
              "y" : 2590,
              "x" : 0,
              "width" : 1080,
              "height" : 335
            },
            "name" : "item3"
          },
          {
            "maskFrame" : null,
            "id" : "ECBAA338-1E7D-432F-812F-FD922611CFB7",
            "visible" : true,
            "children" : [

            ],
            "image" : {
              "path" : "images\/Layer-item2-ECBAA338-1E7D-432F-812F-FD922611CFB7.png",
              "frame" : {
                "y" : 2255,
                "x" : 0,
                "width" : 1080,
                "height" : 335
              }
            },
            "imageType" : "png",
            "layerFrame" : {
              "y" : 2255,
              "x" : 0,
              "width" : 1080,
              "height" : 335
            },
            "name" : "item2"
          },
          {
            "maskFrame" : null,
            "id" : "FE07FAB1-5CD1-42FC-8852-5025075827AB",
            "visible" : true,
            "children" : [

            ],
            "image" : {
              "path" : "images\/Layer-item1-FE07FAB1-5CD1-42FC-8852-5025075827AB.png",
              "frame" : {
                "y" : 1920,
                "x" : 0,
                "width" : 1080,
                "height" : 335
              }
            },
            "imageType" : "png",
            "layerFrame" : {
              "y" : 1920,
              "x" : 0,
              "width" : 1080,
              "height" : 335
            },
            "name" : "item1"
          }
        ],
        "image" : {
          "path" : "images\/Layer-list-29B41A15-BCF6-497C-A793-E45BF7C670E9.png",
          "frame" : {
            "y" : 1920,
            "x" : 0,
            "width" : 1080,
            "height" : 1675
          }
        },
        "imageType" : "png",
        "layerFrame" : {
          "y" : 1920,
          "x" : 0,
          "width" : 1080,
          "height" : 1675
        },
        "name" : "list"
      },
      {
        "maskFrame" : {
          "y" : 0,
          "x" : 0,
          "width" : 1080,
          "height" : 2747
        },
        "id" : "6F3972E7-6E29-4B3C-8CD7-7C742FDDFF83",
        "visible" : true,
        "children" : [
          {
            "maskFrame" : {
              "y" : 286,
              "x" : 40,
              "width" : 1000,
              "height" : 659
            },
            "id" : "6D613359-CC1D-42CF-8DC4-8B7A4A14F5DE",
            "visible" : true,
            "children" : [
              {
                "maskFrame" : null,
                "id" : "A8FC3F29-C82E-44C0-9C36-F6A7B0AD0E4C",
                "visible" : true,
                "children" : [

                ],
                "image" : {
                  "path" : "images\/Layer-realtime-A8FC3F29-C82E-44C0-9C36-F6A7B0AD0E4C.png",
                  "frame" : {
                    "y" : 286,
                    "x" : 40,
                    "width" : 101,
                    "height" : 95
                  }
                },
                "imageType" : "png",
                "layerFrame" : {
                  "y" : 286,
                  "x" : 40,
                  "width" : 101,
                  "height" : 95
                },
                "name" : "realtime"
              },
              {
                "maskFrame" : null,
                "id" : "EA953988-9222-4766-AF30-2B20A28B6F9D",
                "visible" : true,
                "children" : [

                ],
                "image" : {
                  "path" : "images\/Layer-overflow-EA953988-9222-4766-AF30-2B20A28B6F9D.png",
                  "frame" : {
                    "y" : 286,
                    "x" : 939,
                    "width" : 101,
                    "height" : 95
                  }
                },
                "imageType" : "png",
                "layerFrame" : {
                  "y" : 286,
                  "x" : 939,
                  "width" : 101,
                  "height" : 95
                },
                "name" : "overflow"
              },
              {
                "maskFrame" : null,
                "id" : "58F46C0F-BEA5-46E6-A862-B0374E81474F",
                "visible" : true,
                "children" : [

                ],
                "image" : {
                  "path" : "images\/Layer-overlay-58F46C0F-BEA5-46E6-A862-B0374E81474F.png",
                  "frame" : {
                    "y" : 332,
                    "x" : 83,
                    "width" : 915,
                    "height" : 567
                  }
                },
                "imageType" : "png",
                "layerFrame" : {
                  "y" : 332,
                  "x" : 83,
                  "width" : 915,
                  "height" : 567
                },
                "name" : "overlay"
              },
              {
                "maskFrame" : null,
                "id" : "E020EBB4-E9A4-471D-AC53-FAB8B24E4303",
                "visible" : true,
                "children" : [

                ],
                "image" : {
                  "path" : "images\/Layer-chart-E020EBB4-E9A4-471D-AC53-FAB8B24E4303.png",
                  "frame" : {
                    "y" : 445,
                    "x" : 40,
                    "width" : 3000,
                    "height" : 501
                  }
                },
                "imageType" : "png",
                "layerFrame" : {
                  "y" : 445,
                  "x" : 40,
                  "width" : 3000,
                  "height" : 501
                },
                "name" : "chart"
              }
            ],
            "image" : {
              "path" : "images\/Layer-cardOne-6D613359-CC1D-42CF-8DC4-8B7A4A14F5DE.png",
              "frame" : {
                "y" : 286,
                "x" : 40,
                "width" : 1000,
                "height" : 659
              }
            },
            "imageType" : "png",
            "layerFrame" : {
              "y" : 286,
              "x" : 40,
              "width" : 1000,
              "height" : 659
            },
            "name" : "cardOne"
          },
          {
            "maskFrame" : {
              "y" : 983,
              "x" : 40,
              "width" : 1000,
              "height" : 658
            },
            "id" : "CA6B1AD3-3DAC-42CE-ACAE-8CF687BC7185",
            "visible" : true,
            "children" : [
              {
                "maskFrame" : null,
                "id" : "8927AF12-CBA5-4D5C-BB8C-FF3B6E856ACB",
                "visible" : true,
                "children" : [

                ],
                "image" : {
                  "path" : "images\/Layer-realtime-8927AF12-CBA5-4D5C-BB8C-FF3B6E856ACB.png",
                  "frame" : {
                    "y" : 983,
                    "x" : 40,
                    "width" : 101,
                    "height" : 95
                  }
                },
                "imageType" : "png",
                "layerFrame" : {
                  "y" : 983,
                  "x" : 40,
                  "width" : 101,
                  "height" : 95
                },
                "name" : "realtime"
              },
              {
                "maskFrame" : null,
                "id" : "B64F8723-1D8D-45A8-AEE3-2A6430BCA4B2",
                "visible" : true,
                "children" : [

                ],
                "image" : {
                  "path" : "images\/Layer-overflow-B64F8723-1D8D-45A8-AEE3-2A6430BCA4B2.png",
                  "frame" : {
                    "y" : 983,
                    "x" : 939,
                    "width" : 101,
                    "height" : 94
                  }
                },
                "imageType" : "png",
                "layerFrame" : {
                  "y" : 983,
                  "x" : 939,
                  "width" : 101,
                  "height" : 94
                },
                "name" : "overflow"
              },
              {
                "maskFrame" : null,
                "id" : "1E94A53A-9EF3-41AA-A752-63C5B3B82735",
                "visible" : true,
                "children" : [

                ],
                "image" : {
                  "path" : "images\/Layer-overlay-1E94A53A-9EF3-41AA-A752-63C5B3B82735.png",
                  "frame" : {
                    "y" : 1030,
                    "x" : 82,
                    "width" : 916,
                    "height" : 567
                  }
                },
                "imageType" : "png",
                "layerFrame" : {
                  "y" : 1030,
                  "x" : 82,
                  "width" : 916,
                  "height" : 567
                },
                "name" : "overlay"
              },
              {
                "maskFrame" : null,
                "id" : "9CB5AEF0-E0F4-41E3-AA26-04A624009EED",
                "visible" : true,
                "children" : [

                ],
                "image" : {
                  "path" : "images\/Layer-chart-9CB5AEF0-E0F4-41E3-AA26-04A624009EED.png",
                  "frame" : {
                    "y" : 1139,
                    "x" : 40,
                    "width" : 3001,
                    "height" : 501
                  }
                },
                "imageType" : "png",
                "layerFrame" : {
                  "y" : 1139,
                  "x" : 40,
                  "width" : 3001,
                  "height" : 501
                },
                "name" : "chart"
              }
            ],
            "image" : {
              "path" : "images\/Layer-cardTwo-CA6B1AD3-3DAC-42CE-ACAE-8CF687BC7185.png",
              "frame" : {
                "y" : 983,
                "x" : 40,
                "width" : 1000,
                "height" : 658
              }
            },
            "imageType" : "png",
            "layerFrame" : {
              "y" : 983,
              "x" : 40,
              "width" : 1000,
              "height" : 658
            },
            "name" : "cardTwo"
          },
          {
            "maskFrame" : {
              "y" : 2045,
              "x" : 40,
              "width" : 1000,
              "height" : 659
            },
            "id" : "CBFF37BF-4BF1-47DB-98F2-60BBA5D0B4A4",
            "visible" : true,
            "children" : [
              {
                "maskFrame" : null,
                "id" : "26D16290-A206-4031-BFA3-AD40F70D244B",
                "visible" : true,
                "children" : [

                ],
                "image" : {
                  "path" : "images\/Layer-realtime-26D16290-A206-4031-BFA3-AD40F70D244B.png",
                  "frame" : {
                    "y" : 2046,
                    "x" : 40,
                    "width" : 101,
                    "height" : 95
                  }
                },
                "imageType" : "png",
                "layerFrame" : {
                  "y" : 2046,
                  "x" : 40,
                  "width" : 101,
                  "height" : 95
                },
                "name" : "realtime"
              },
              {
                "maskFrame" : null,
                "id" : "3588A54D-4900-4E3B-BBBD-84EBF0022F5A",
                "visible" : true,
                "children" : [

                ],
                "image" : {
                  "path" : "images\/Layer-overflow-3588A54D-4900-4E3B-BBBD-84EBF0022F5A.png",
                  "frame" : {
                    "y" : 2045,
                    "x" : 939,
                    "width" : 101,
                    "height" : 95
                  }
                },
                "imageType" : "png",
                "layerFrame" : {
                  "y" : 2045,
                  "x" : 939,
                  "width" : 101,
                  "height" : 95
                },
                "name" : "overflow"
              },
              {
                "maskFrame" : null,
                "id" : "F699E05D-6AC8-4335-9634-09C1399E83D3",
                "visible" : true,
                "children" : [

                ],
                "image" : {
                  "path" : "images\/Layer-overlay-F699E05D-6AC8-4335-9634-09C1399E83D3.png",
                  "frame" : {
                    "y" : 2092,
                    "x" : 82,
                    "width" : 916,
                    "height" : 567
                  }
                },
                "imageType" : "png",
                "layerFrame" : {
                  "y" : 2092,
                  "x" : 82,
                  "width" : 916,
                  "height" : 567
                },
                "name" : "overlay"
              },
              {
                "maskFrame" : null,
                "id" : "95DDE806-17FA-4ACF-9E9B-1CB45396D697",
                "visible" : true,
                "children" : [

                ],
                "image" : {
                  "path" : "images\/Layer-chart-95DDE806-17FA-4ACF-9E9B-1CB45396D697.png",
                  "frame" : {
                    "y" : 2046,
                    "x" : 40,
                    "width" : 3001,
                    "height" : 659
                  }
                },
                "imageType" : "png",
                "layerFrame" : {
                  "y" : 2046,
                  "x" : 40,
                  "width" : 3001,
                  "height" : 659
                },
                "name" : "chart"
              }
            ],
            "image" : {
              "path" : "images\/Layer-cardThree-CBFF37BF-4BF1-47DB-98F2-60BBA5D0B4A4.png",
              "frame" : {
                "y" : 2045,
                "x" : 40,
                "width" : 1000,
                "height" : 659
              }
            },
            "imageType" : "png",
            "layerFrame" : {
              "y" : 2045,
              "x" : 40,
              "width" : 1000,
              "height" : 659
            },
            "name" : "cardThree"
          },
          {
            "maskFrame" : null,
            "children" : [
              {
                "maskFrame" : {
                  "y" : 1579,
                  "x" : 1020,
                  "width" : 1200,
                  "height" : 858
                },
                "id" : "D6DDD9B5-78CB-497A-A5B2-18936D7502AC",
                "visible" : true,
                "children" : [

                ],
                "image" : {
                  "path" : "images\/Layer-cardA-D6DDD9B5-78CB-497A-A5B2-18936D7502AC.png",
                  "frame" : {
                    "y" : 1679,
                    "x" : 1120,
                    "width" : 1000,
                    "height" : 658
                  }
                },
                "imageType" : "png",
                "layerFrame" : {
                  "y" : 1679,
                  "x" : 1120,
                  "width" : 1000,
                  "height" : 658
                },
                "name" : "cardA"
              },
              {
                "maskFrame" : {
                  "y" : 1679,
                  "x" : 580,
                  "width" : 500,
                  "height" : 658
                },
                "id" : "48278F88-0D95-42FE-9CC6-5A6C6153DBFC",
                "visible" : true,
                "children" : [

                ],
                "image" : {
                  "path" : "images\/Layer-cardB-48278F88-0D95-42FE-9CC6-5A6C6153DBFC.png",
                  "frame" : {
                    "y" : 1679,
                    "x" : 580,
                    "width" : 1000,
                    "height" : 658
                  }
                },
                "imageType" : "png",
                "layerFrame" : {
                  "y" : 1679,
                  "x" : 580,
                  "width" : 1000,
                  "height" : 658
                },
                "name" : "cardB"
              },
              {
                "maskFrame" : {
                  "y" : 1679,
                  "x" : 40,
                  "width" : 1000,
                  "height" : 658
                },
                "id" : "38A8AA46-7213-417F-AAB6-3B94483849BC",
                "visible" : true,
                "children" : [

                ],
                "image" : {
                  "path" : "images\/Layer-cardC-38A8AA46-7213-417F-AAB6-3B94483849BC.png",
                  "frame" : {
                    "y" : 1679,
                    "x" : 40,
                    "width" : 1000,
                    "height" : 658
                  }
                },
                "imageType" : "png",
                "layerFrame" : {
                  "y" : 1679,
                  "x" : 40,
                  "width" : 1000,
                  "height" : 658
                },
                "name" : "cardC"
              }
            ],
            "id" : "F3BAC779-067A-45B9-8E26-A6FB0F195A8F",
            "visible" : true,
            "imageType" : "png",
            "layerFrame" : {
              "y" : 1679,
              "x" : 40,
              "width" : 2080,
              "height" : 658
            },
            "name" : "smallScroll"
          }
        ],
        "image" : {
          "path" : "images\/Layer-content-6F3972E7-6E29-4B3C-8CD7-7C742FDDFF83.png",
          "frame" : {
            "y" : 0,
            "x" : 0,
            "width" : 1080,
            "height" : 2747
          }
        },
        "imageType" : "png",
        "layerFrame" : {
          "y" : 0,
          "x" : 0,
          "width" : 1080,
          "height" : 2747
        },
        "name" : "content"
      }
    ],
    "image" : {
      "path" : "images\/Layer-iot-CD7C7C7A-40BD-4449-884D-CE043DD9C73B.png",
      "frame" : {
        "y" : -19,
        "x" : -20,
        "width" : 1120,
        "height" : 3614
      }
    },
    "imageType" : "png",
    "layerFrame" : {
      "y" : -19,
      "x" : -20,
      "width" : 1120,
      "height" : 3614
    },
    "name" : "iot"
  }
]